{
  "$schema": "http://json-schema.org/draft-07/schema",
  "id": "3DTILES_temporal.batchTable.schema.json",
  "title": "3DTILES_temporal_batch_table extension",
  "type": "object",
  "description": "Specifies the properties of 3DTILES_temporal extension stored in the batch table",
  "properties": {
    "startDates": {
      "description": "Start dates of existence of the features in the real world. Dates are organized according to the batch id (same as for the batch table)",
      "type": "array",
      "items": {
        "type": "string",
        "format": "date"
      }
    },
    "endDates": {
      "description": "End dates of existence of the features in the real world. Dates are organized according to the batch id (same as for the batch table)",
      "type": "array",
      "items": {
        "type": "string",
        "format": "date"
      }
    },
    "featureIds": {
      "description": "Array of ids of the features. Used in versions and transactions to identify the features.",
      "type": "array",
      "items": {"type": "string"}
    }
  }
}
